CONTRIBUTING.md
HISTORY.md
LICENSE
MANIFEST.in
README.md
setup.cfg
setup.py
alexafsm/__init__.py
alexafsm/amazon_intent.py
alexafsm/make_json_serializable.py
alexafsm/policy.py
alexafsm/response.py
alexafsm/session_attributes.py
alexafsm/states.py
alexafsm/test_helpers.py
alexafsm/utils.py
alexafsm.egg-info/PKG-INFO
alexafsm.egg-info/SOURCES.txt
alexafsm.egg-info/dependency_links.txt
alexafsm.egg-info/not-zip-safe
alexafsm.egg-info/requires.txt
alexafsm.egg-info/top_level.txt
tests/__init__.py
tests/test_session_attributes.py
tests/test_skillsearch.py
tests/skillsearch/README.md
tests/skillsearch/__init__.py
tests/skillsearch/clients.py
tests/skillsearch/dynamodb.py
tests/skillsearch/fsm.png
tests/skillsearch/intent.py
tests/skillsearch/machine.txt
tests/skillsearch/policy.py
tests/skillsearch/server.py
tests/skillsearch/session_attributes.py
tests/skillsearch/skill.py
tests/skillsearch/skill_settings.py
tests/skillsearch/states.py
tests/skillsearch/bin/graph.py
tests/skillsearch/bin/graph.sh
tests/skillsearch/bin/print-machine.sh
tests/skillsearch/bin/print_machine.py
tests/skillsearch/speech/alexa-schema.json
tests/skillsearch/speech/sample-utterances.txt
tests/skillsearch/speech/slot-types/NTH.txt
tests/skillsearch/speech/slot-types/QUERY.txt