Metadata-Version: 1.1
Name: alexafsm
Version: 0.1.11
Summary: Finite-state machine library for building complex Alexa conversations
Home-page: https://github.com/allenai/alexafsm
Author: Allen AI
Author-email: a-dialog-research@allenai.org
License: Apache Software License 2.0
Keywords: alexafsm,alexa skill,finite-state machine,fsm,dialog,dialog state management
Platform: UNKNOWN
Classifier: Development Status :: 2 - Pre-Alpha
Classifier: Intended Audience :: Developers
Classifier: License :: OSI Approved :: Apache Software License
Classifier: Natural Language :: English
Classifier: Programming Language :: Python :: 3.6
